pygpukit/__init__.py
pygpukit/_native_loader.py
pygpukit/_pygpukit_native_cu131.cpython-312-x86_64-linux-gnu.so
pygpukit/_pygpukit_rust.cpython-312-x86_64-linux-gnu.so
pygpukit/asr/__init__.py
pygpukit/asr/preprocessing.py
pygpukit/asr/whisper/__init__.py
pygpukit/asr/whisper/config.py
pygpukit/asr/whisper/decoder.py
pygpukit/asr/whisper/encoder.py
pygpukit/asr/whisper/loader.py
pygpukit/asr/whisper/model.py
pygpukit/benchmark/__init__.py
pygpukit/benchmark/__main__.py
pygpukit/benchmark/attention.py
pygpukit/benchmark/base.py
pygpukit/benchmark/cli.py
pygpukit/benchmark/gemm.py
pygpukit/benchmark/gemv.py
pygpukit/benchmark/results.py
pygpukit/core/__init__.py
pygpukit/core/array.py
pygpukit/core/backend.py
pygpukit/core/device.py
pygpukit/core/dtypes.py
pygpukit/core/factory.py
pygpukit/core/memory.py
pygpukit/core/stream.py
pygpukit/diffusion/__init__.py
pygpukit/diffusion/config.py
pygpukit/diffusion/pipeline.py
pygpukit/diffusion/models/__init__.py
pygpukit/diffusion/models/dit_base.py
pygpukit/diffusion/models/vae.py
pygpukit/diffusion/models/dit/__init__.py
pygpukit/diffusion/models/dit/adaln.py
pygpukit/diffusion/models/dit/attention.py
pygpukit/diffusion/models/dit/embeddings.py
pygpukit/diffusion/models/dit/ffn.py
pygpukit/diffusion/models/dit/model.py
pygpukit/diffusion/models/flux/__init__.py
pygpukit/diffusion/models/flux/attention.py
pygpukit/diffusion/models/flux/blocks.py
pygpukit/diffusion/models/flux/embeddings.py
pygpukit/diffusion/models/flux/model.py
pygpukit/diffusion/models/flux/ops.py
pygpukit/diffusion/models/flux/pipeline.py
pygpukit/diffusion/models/flux/scheduler.py
pygpukit/diffusion/ops/__init__.py
pygpukit/diffusion/ops/adaln.py
pygpukit/diffusion/ops/conv2d.py
pygpukit/diffusion/ops/cross_attention.py
pygpukit/diffusion/ops/group_norm.py
pygpukit/diffusion/ops/timestep_embed.py
pygpukit/diffusion/scheduler/__init__.py
pygpukit/diffusion/scheduler/base.py
pygpukit-0.2.19.dist-info/METADATA
pygpukit-0.2.19.dist-info/WHEEL
pygpukit-0.2.19.dist-info/RECORD
pygpukit-0.2.19.dist-info/licenses/LICENSE
