Metadata-Version: 2.4
Name: PyGPUkit
Version: 0.2.19
Summary: A lightweight GPU runtime for Python with Rust-powered scheduler, NVRTC JIT compilation, and NumPy-like API
Keywords: gpu,cuda,nvrtc,jit,numpy,array
Author: m96-chan
License-Expression: MIT
Classifier: Development Status :: 3 - Alpha
Classifier: Intended Audience :: Developers
Classifier: Intended Audience :: Science/Research
Classifier: Operating System :: POSIX :: Linux
Classifier: Operating System :: Microsoft :: Windows
Classifier: Programming Language :: Python :: 3
Classifier: Programming Language :: Python :: 3.10
Classifier: Programming Language :: Python :: 3.11
Classifier: Programming Language :: Python :: 3.12
Classifier: Programming Language :: Python :: 3.13
Classifier: Programming Language :: Python :: 3.14
Classifier: Topic :: Scientific/Engineering
Classifier: Topic :: Software Development :: Libraries :: Python Modules
Project-URL: Homepage, https://github.com/m96-chan/PyGPUkit
Project-URL: Repository, https://github.com/m96-chan/PyGPUkit
Project-URL: Issues, https://github.com/m96-chan/PyGPUkit/issues
Requires-Python: >=3.10
Requires-Dist: numpy>=1.20.0
Provides-Extra: dev
Requires-Dist: pytest>=7.0.0; extra == "dev"
Requires-Dist: pytest-cov>=4.0.0; extra == "dev"
Requires-Dist: ruff>=0.1.0; extra == "dev"
Requires-Dist: mypy>=1.0.0; extra == "dev"
Requires-Dist: psutil>=5.0.0; extra == "dev"
Requires-Dist: pre-commit>=3.0.0; extra == "dev"
Provides-Extra: triton
Requires-Dist: triton>=3.0.0; extra == "triton"
